stochastic_matching/__init__.py
stochastic_matching/common.py
stochastic_matching/display.py
stochastic_matching/graphs.py
stochastic_matching/model.py
stochastic_matching/simulator/__init__.py
stochastic_matching/simulator/arrivals.py
stochastic_matching/simulator/e_filtering.py
stochastic_matching/simulator/extended.py
stochastic_matching/simulator/fcfm.py
stochastic_matching/simulator/graph.py
stochastic_matching/simulator/logs.py
stochastic_matching/simulator/longest.py
stochastic_matching/simulator/metrics.py
stochastic_matching/simulator/multiqueue.py
stochastic_matching/simulator/parallel.py
stochastic_matching/simulator/priority.py
stochastic_matching/simulator/random_edge.py
stochastic_matching/simulator/random_item.py
stochastic_matching/simulator/simulator.py
stochastic_matching/simulator/virtual_queue.py
stochastic_matching-0.3.3.dist-info/AUTHORS.rst
stochastic_matching-0.3.3.dist-info/LICENSE
stochastic_matching-0.3.3.dist-info/METADATA
stochastic_matching-0.3.3.dist-info/WHEEL
stochastic_matching-0.3.3.dist-info/RECORD
