Metadata-Version: 2.1
Name: stochastic-matching
Version: 0.3.3
Summary: Stochastic Matching provides tools to analyze the behavior of stochastic matching problems.
License: GPLv3
Author: Fabien Mathieu
Author-email: fabien.mathieu@normalesup.org
Requires-Python: >=3.10,<4.0
Classifier: License :: Other/Proprietary License
Classifier: Programming Language :: Python :: 3
Classifier: Programming Language :: Python :: 3.10
Classifier: Programming Language :: Python :: 3.11
Classifier: Programming Language :: Python :: 3.12
Requires-Dist: cached-property (>=1.5.2,<2.0.0)
Requires-Dist: ipython (>=8.24.0,<9.0.0)
Requires-Dist: matplotlib (>=3.9.0,<4.0.0)
Requires-Dist: multiprocess (>=0.70.16,<0.71.0)
Requires-Dist: numba (>=0.59.1,<0.60.0)
Requires-Dist: scipy (>=1.13.0,<2.0.0)
Requires-Dist: tqdm (>=4.66.4,<5.0.0)
